near/__init__.py
near/context.py
near/economics.py
near/math.py
near/misc.py
near/promises.py
near/py.typed
near/registers.py
near/storage.py
near/types.py
near/validator.py
near_sdk_py/__init__.py
near_sdk_py/constants.py
near_sdk_py/context.py
near_sdk_py/contract.py
near_sdk_py/decorators.py
near_sdk_py/input.py
near_sdk_py/log.py
near_sdk_py/py.typed
near_sdk_py/storage.py
near_sdk_py/value_return.py
near_sdk_py/collections/__init__.py
near_sdk_py/collections/adapter.py
near_sdk_py/collections/base.py
near_sdk_py/collections/lookup_map.py
near_sdk_py/collections/lookup_set.py
near_sdk_py/collections/tree_map.py
near_sdk_py/collections/unordered_map.py
near_sdk_py/collections/unordered_set.py
near_sdk_py/collections/utils.py
near_sdk_py/collections/vector.py
near_sdk_py/promises/__init__.py
near_sdk_py/promises/batch.py
near_sdk_py/promises/contract.py
near_sdk_py/promises/decorators.py
near_sdk_py/promises/promise.py
near_sdk_py-1.0.0.dist-info/METADATA
near_sdk_py-1.0.0.dist-info/WHEEL
near_sdk_py-1.0.0.dist-info/licenses/LICENSE
near_sdk_py-1.0.0.dist-info/RECORD
