Metadata-Version: 2.4
Name: near-sdk-py
Version: 1.0.0
Summary: A higher-level API for building NEAR smart contracts in Python.
License-File: LICENSE
Requires-Python: >=3.11
